django-times/__init__.py
django-times/apps.py
django-times/utils.py
django-times/templatetags/__init__.py
django-times/templatetags/django_times.py
django_times/__init__.py
django_times/apps.py
django_times/utils.py
django_times/static/__init__.py
django_times/static/django_times/clock.js
django_times/static/django_times/clock_12.js
django_times/templatetags/__init__.py
django_times/templatetags/django_times.py
django_times-0.1.3.dist-info/LICENCE
django_times-0.1.3.dist-info/METADATA
django_times-0.1.3.dist-info/WHEEL
django_times-0.1.3.dist-info/top_level.txt
django_times-0.1.3.dist-info/RECORD
