Metadata-Version: 2.1
Name: django-times
Version: 0.1.3
Summary: Una biblioteca para trabajar con fechas y horas en Django dentro de los templates.
Home-page: https://github.com/estuardodev/django-times
Download-URL: https://github.com/estuardodev/django-times.git
Author: Estuardo Ramírez
Author-email: contacto@estuardo.dev
Keywords: estuardodev,django-times,django,times,python times,python,times django
Classifier: Development Status :: 4 - Beta
Classifier: Environment :: Console
Classifier: Environment :: Web Environment
Classifier: Intended Audience :: End Users/Desktop
Classifier: Intended Audience :: Developers
Classifier: Intended Audience :: System Administrators
Classifier: License :: OSI Approved :: MIT License
Classifier: Operating System :: MacOS :: MacOS X
Classifier: Operating System :: Microsoft :: Windows
Classifier: Operating System :: POSIX
Classifier: Programming Language :: Python
Classifier: Programming Language :: Python :: 3
Classifier: Programming Language :: Python :: 3.2
Classifier: Programming Language :: Python :: 3.3
Classifier: Programming Language :: Python :: 3.4
Classifier: Programming Language :: Python :: 3.5
Classifier: Programming Language :: Python :: 3.6
Classifier: Programming Language :: Python :: 3.7
Classifier: Programming Language :: Python :: 3.8
Classifier: Programming Language :: Python :: 3.9
Classifier: Programming Language :: Python :: 3.10
Classifier: Programming Language :: Python :: 3.11
Classifier: Topic :: Office/Business
Classifier: Topic :: Software Development :: Bug Tracking
License-File: LICENCE
Requires-Dist: Django >=3.2
Requires-Dist: pytz
Requires-Dist: babel
